<annotation>
	<folder>unlabeled_data</folder>
	<filename>dog.297.jpg</filename>
	<path>/home/alvaro/Área de Trabalho/tf-models/research/object_detection/unlabeled_data/dog.297.jpg</path>
	<source>
		<database>Unknown</database>
	</source>
	<size>
		<width>160</width>
		<height>199</height>
		<depth>3</depth>
	</size>
	<segmented>0</segmented>
	<object>
		<name>dog</name>
		<pose>Unspecified</pose>
		<truncated>1</truncated>
		<difficult>0</difficult>
		<bndbox>
			<xmin>20</xmin>
			<ymin>3</ymin>
			<xmax>159</xmax>
			<ymax>199</ymax>
		</bndbox>
	</object>
</annotation>
